linlog/__init__.py
linlog/cli.py
linlog/client.py
linlog/constants.py
linlog/controller.py
linlog/model_trainer.py
linlog/utils.py
linlog/commands/__init__.py
linlog/commands/authenticate.py
linlog/commands/datasets.py
linlog/commands/projects.py
linlog/commands/remote_dataset_save.py
linlog/data_types/__init__.py
linlog/data_types/labels.py
linlog/data_types/task.py
linlog/dataset/__init__.py
linlog/dataset/base_dataset.py
linlog/dataset/local_dataset.py
linlog/dataset/remote_dataset.py
linlog/exporter/__init__.py
linlog/exporter/formats/__init__.py
linlog/exporter/formats/coco.py
linlog/exporter/formats/linlog.py
linlog/exporter/formats/spacy.py
linlog/exporter/formats/tensorflow.py
linlog/tensorflow/__init__.py
linlog/tensorflow/dataset.py
linlog/tensorflow/formatter.py
linlog/tensorflow/utils.py
linlog/tests/__init__.py
linlog/tests/test_client.py
linlog/torch/__init__.py
linlog/torch/dataset.py
tests/__init__.py
tests/test_client.py
linearlogic-0.3.4.dist-info/METADATA
linearlogic-0.3.4.dist-info/WHEEL
linearlogic-0.3.4.dist-info/entry_points.txt
linearlogic-0.3.4.dist-info/top_level.txt
linearlogic-0.3.4.dist-info/RECORD
