Metadata-Version: 2.1
Name: linearlogic
Version: 0.3.4
Summary: Linear Logic Python SDK
Home-page: https://linearlogic.ai
Author: Linear Logic Inc.
Author-email: support@linearlogic.ai
Classifier: Programming Language :: Python :: 3
Classifier: License :: OSI Approved :: MIT License
Classifier: Operating System :: OS Independent
Requires-Dist: awesome-progress-bar (>=1.7.2)
Requires-Dist: requests (>=2.28.1)
Requires-Dist: colored (==1.4.3)
